logformat/__init__.py
logformat/py.typed
logformat-0.1.0.dist-info/METADATA
logformat-0.1.0.dist-info/WHEEL
logformat-0.1.0.dist-info/licenses/LICENSE
logformat-0.1.0.dist-info/RECORD
