Metadata-Version: 2.4
Name: logformat
Version: 0.1.0
Summary: logfmt logging for Python
Project-URL: repository, https://git.push-f.com/logformat
Author-email: Martin Fischer <martin@push-f.com>
License-Expression: MIT
License-File: LICENSE
Classifier: Operating System :: OS Independent
Classifier: Programming Language :: Python :: 3
Requires-Python: >=3.13
